{
  "type": "Feature",
  "stac_version": "1.1.0",
  "collection": "sentinel-3-syn-2-aod-ntc",
  "id": "S3A_SY_2_AOD____20240101T002426_20240101T010826_20240102T163130_2640_107_216______PS1_O_NT_002",
  "properties": {
    "created": "2024-01-02T16:42:00.741000Z",
    "updated": "2024-01-02T16:49:15.588352Z",
    "published": "2024-01-02T16:49:14.163430Z",
    "eopf:origin_datetime": "2024-01-02T16:42:00.741000Z",
    "auth:schemes": {
      "s3": {
        "type": "s3"
      },
      "oidc": {
        "type": "openIdConnect",
        "openIdConnectUrl": "https://identity.dataspace.copernicus.eu/auth/realms/CDSE/.well-known/openid-configuration"
      }
    },
    "storage:schemes": {
      "cdse-s3": {
        "title": "Copernicus Data Space Ecosystem S3",
        "description": "This endpoint provides access to EO data which is stored on the object storage of both CloudFerro Cloud and OpenTelekom Cloud (OTC). See the [documentation](https://documentation.dataspace.copernicus.eu/APIs/S3.html) for more information, including how to get credentials.",
        "platform": "https://eodata.dataspace.copernicus.eu",
        "requester_pays": false,
        "type": "custom-s3"
      },
      "creodias-s3": {
        "title": "CREODIAS S3",
        "description": "Comprehensive Earth Observation Data (EODATA) archive offered by CREODIAS as a commercial part of CDSE, designed to provide users with access to a vast repository of satellite data without predefined quota limits.",
        "platform": "https://eodata.cloudferro.com",
        "requester_pays": true,
        "type": "custom-s3"
      }
    },
    "datetime": "2024-01-01T00:24:25.696511Z",
    "start_datetime": "2024-01-01T00:24:25.696511Z",
    "end_datetime": "2024-01-01T01:08:26.256020Z",
    "platform": "sentinel-3a",
    "constellation": "sentinel-3",
    "instruments": [
      "olci",
      "slstr"
    ],
    "gsd": 4500,
    "processing:level": "L2",
    "processing:datetime": "2024-01-02T14:50:15.762173Z",
    "proj:code": null,
    "sat:absolute_orbit": 40999,
    "sat:relative_orbit": 216,
    "sat:orbit_cycle": 107,
    "sat:orbit_state": "descending",
    "sat:platform_international_designator": "2016-011A",
    "eo:cloud_cover": 83.87,
    "product:type": "SY_2_AOD___",
    "product:timeliness": "P1M",
    "product:timeliness_category": "NT",
    "statistics": {
      "saline_water": 64.631407,
      "land": 35.342788
    },
    "processing:version": "01.09",
    "processing:software": {
      "eometadatatool": "250924131919+dirty"
    },
    "expires": "9999-01-01T00:00:00.000000Z"
  },
  "bbox": [
    -18.2498,
    -84.3895,
    161.68,
    57.5712
  ],
  "geometry": {
    "type": "Polygon",
    "coordinates": [
      [
        [
          141.735,
          57.57119999999999
        ],
        [
          138.278,
          36.0127
        ],
        [
          135.548,
          20.5622
        ],
        [
          133.35299999999998,
          9.22036
        ],
        [
          131.59799999999998,
          0.9800550000000001
        ],
        [
          129.66200000000003,
          -7.24078
        ],
        [
          127.489,
          -15.429800000000002
        ],
        [
          125.648,
          -21.5387
        ],
        [
          123.57,
          -27.608899999999995
        ],
        [
          121.59999999999997,
          -32.6271
        ],
        [
          119.355,
          -37.5993
        ],
        [
          116.758,
          -42.51369999999999
        ],
        [
          114.346,
          -46.3885
        ],
        [
          111.54899999999999,
          -50.198100000000004
        ],
        [
          108.25499999999998,
          -53.9223
        ],
        [
          105.36899999999999,
          -56.6438
        ],
        [
          102.034,
          -59.2839
        ],
        [
          99.50949999999999,
          -60.98929999999999
        ],
        [
          95.1779,
          -63.443699999999986
        ],
        [
          91.86339999999998,
          -64.9958
        ],
        [
          88.1494,
          -66.46359999999999
        ],
        [
          84.00529999999999,
          -67.8412
        ],
        [
          79.353,
          -69.0945
        ],
        [
          74.1588,
          -70.20009999999999
        ],
        [
          65.3667,
          -71.5445
        ],
        [
          58.89589999999998,
          -72.2026
        ],
        [
          52.02649999999999,
          -72.624
        ],
        [
          44.92399999999999,
          -72.7931
        ],
        [
          37.7864,
          -72.70979999999999
        ],
        [
          27.4584,
          -72.1073
        ],
        [
          18.0243,
          -71.01149999999998
        ],
        [
          12.332,
          -70.0259
        ],
        [
          10.3873,
          -71.1114
        ],
        [
          6.9333,
          -72.74
        ],
        [
          4.08993,
          -73.8532
        ],
        [
          -0.048603999999999994,
          -75.18069999999999
        ],
        [
          -4.457299999999999,
          -76.3139
        ],
        [
          -9.10147,
          -77.2589
        ],
        [
          -18.2498,
          -78.60209999999998
        ],
        [
          -12.001899999999997,
          -80.33589999999998
        ],
        [
          -8.01111,
          -81.1537
        ],
        [
          -3.26051,
          -81.92359999999998
        ],
        [
          2.4225,
          -82.62949999999998
        ],
        [
          9.20097,
          -83.2525
        ],
        [
          17.1962,
          -83.76769999999999
        ],
        [
          26.4005,
          -84.14599999999999
        ],
        [
          36.5696,
          -84.3591
        ],
        [
          47.1816,
          -84.38949999999998
        ],
        [
          57.56380000000001,
          -84.2343
        ],
        [
          67.12429999999999,
          -83.9072
        ],
        [
          75.52839999999999,
          -83.4342
        ],
        [
          82.7006,
          -82.8442
        ],
        [
          88.72749999999999,
          -82.16320000000002
        ],
        [
          93.7681,
          -81.4128
        ],
        [
          97.9963,
          -80.6098
        ],
        [
          104.60399999999998,
          -78.8919
        ],
        [
          109.47299999999998,
          -77.0745
        ],
        [
          113.193,
          -75.194
        ],
        [
          114.744,
          -74.23709999999998
        ],
        [
          117.38,
          -72.29919999999998
        ],
        [
          119.549,
          -70.33609999999999
        ],
        [
          121.37600000000002,
          -68.3549
        ],
        [
          122.95300000000002,
          -66.3612
        ],
        [
          124.31199999999997,
          -64.35449999999999
        ],
        [
          126.066,
          -61.328900000000004
        ],
        [
          127.565,
          -58.28799999999998
        ],
        [
          128.877,
          -55.2361
        ],
        [
          130.412,
          -51.152100000000004
        ],
        [
          132.995,
          -42.9469
        ],
        [
          135.438,
          -33.6713
        ],
        [
          137.622,
          -24.3615
        ],
        [
          144.95999999999998,
          8.867869999999998
        ],
        [
          147.508,
          19.235099999999996
        ],
        [
          149.79499999999996,
          27.498699999999996
        ],
        [
          152.436,
          35.718
        ],
        [
          155.193,
          42.8562
        ],
        [
          158.066,
          48.91499999999999
        ],
        [
          159.753,
          51.9163
        ],
        [
          161.68,
          54.9165
        ],
        [
          157.497,
          55.78119999999999
        ],
        [
          152.389,
          56.605599999999995
        ],
        [
          146.66099999999997,
          57.241
        ],
        [
          141.735,
          57.57119999999999
        ]
      ]
    ]
  },
  "links": [
    {
      "rel": "version-history",
      "href": "https://trace.dataspace.copernicus.eu/api/v1/traces/name/S3A_SY_2_AOD____20240101T002426_20240101T010826_20240102T163130_2640_107_216______PS1_O_NT_002.SEN3.zip",
      "type": "application/json",
      "title": "Product history record from the CDSE traceability service"
    },
    {
      "rel": "enclosure",
      "href": "s3://eodata/Sentinel-3/SYNERGY/SY_2_AOD___/2024/01/01/S3A_SY_2_AOD____20240101T002426_20240101T010826_20240102T163130_2640_107_216______PS1_O_NT_002.SEN3/",
      "type": "application/x-directory",
      "title": "S3 path to source directory",
      "auth:refs": [
        "s3"
      ],
      "storage:refs": [
        "cdse-s3",
        "creodias-s3"
      ]
    }
  ],
  "assets": {
    "ntc_aod_data": {
      "type": "application/netcdf",
      "title": "Global aerosol parameters",
      "roles": [
        "data"
      ],
      "file:checksum": "d50110cafb23db35197c514e8b857f50aaf1b6",
      "file:size": 29669907,
      "file:local_path": "S3A_SY_2_AOD____20240101T002426_20240101T010826_20240102T163130_2640_107_216______PS1_O_NT_002.SEN3/NTC_AOD.nc",
      "href": "s3://eodata/Sentinel-3/SYNERGY/SY_2_AOD___/2024/01/01/S3A_SY_2_AOD____20240101T002426_20240101T010826_20240102T163130_2640_107_216______PS1_O_NT_002.SEN3/NTC_AOD.nc",
      "alternate:name": "S3",
      "auth:refs": [
        "s3"
      ],
      "storage:refs": [
        "cdse-s3",
        "creodias-s3"
      ],
      "alternate": {
        "https": {
          "href": "https://zipper.dataspace.copernicus.eu/odata/v1/Products(2586189a-189b-4f95-b3f9-db8bf6a3d788)/Nodes(S3A_SY_2_AOD____20240101T002426_20240101T010826_20240102T163130_2640_107_216______PS1_O_NT_002.SEN3)/Nodes(NTC_AOD.nc)/$value",
          "alternate:name": "HTTPS",
          "auth:refs": [
            "oidc"
          ],
          "storage:refs": []
        }
      }
    },
    "xfdumanifest": {
      "type": "application/xml",
      "title": "Product manifest",
      "roles": [
        "metadata"
      ],
      "file:local_path": "S3A_SY_2_AOD____20240101T002426_20240101T010826_20240102T163130_2640_107_216______PS1_O_NT_002.SEN3/xfdumanifest.xml",
      "href": "s3://eodata/Sentinel-3/SYNERGY/SY_2_AOD___/2024/01/01/S3A_SY_2_AOD____20240101T002426_20240101T010826_20240102T163130_2640_107_216______PS1_O_NT_002.SEN3/xfdumanifest.xml",
      "alternate:name": "S3",
      "auth:refs": [
        "s3"
      ],
      "storage:refs": [
        "cdse-s3",
        "creodias-s3"
      ],
      "alternate": {
        "https": {
          "href": "https://zipper.dataspace.copernicus.eu/odata/v1/Products(2586189a-189b-4f95-b3f9-db8bf6a3d788)/Nodes(S3A_SY_2_AOD____20240101T002426_20240101T010826_20240102T163130_2640_107_216______PS1_O_NT_002.SEN3)/Nodes(xfdumanifest.xml)/$value",
          "alternate:name": "HTTPS",
          "auth:refs": [
            "oidc"
          ],
          "storage:refs": []
        }
      }
    },
    "product": {
      "type": "application/zip",
      "title": "Zipped product",
      "roles": [
        "data",
        "metadata",
        "archive"
      ],
      "file:checksum": "d501106b7ba96ebfa8f7920cf7470cd0e21a55",
      "file:size": 29716718,
      "file:local_path": "S3A_SY_2_AOD____20240101T002426_20240101T010826_20240102T163130_2640_107_216______PS1_O_NT_002.SEN3.zip",
      "href": "https://download.dataspace.copernicus.eu/odata/v1/Products(2586189a-189b-4f95-b3f9-db8bf6a3d788)/$value",
      "auth:refs": [
        "oidc"
      ]
    }
  },
  "stac_extensions": [
    "https://cs-si.github.io/eopf-stac-extension/v1.2.0/schema.json",
    "https://stac-extensions.github.io/alternate-assets/v1.2.0/schema.json",
    "https://stac-extensions.github.io/authentication/v1.1.0/schema.json",
    "https://stac-extensions.github.io/eo/v2.0.0/schema.json",
    "https://stac-extensions.github.io/file/v2.1.0/schema.json",
    "https://stac-extensions.github.io/processing/v1.2.0/schema.json",
    "https://stac-extensions.github.io/product/v1.0.0/schema.json",
    "https://stac-extensions.github.io/projection/v2.0.0/schema.json",
    "https://stac-extensions.github.io/sat/v1.1.0/schema.json",
    "https://stac-extensions.github.io/storage/v2.0.0/schema.json",
    "https://stac-extensions.github.io/timestamps/v1.1.0/schema.json"
  ]
}